sigma/backends/kernellix/__init__.py
sigma/backends/kernellix/kernellix.py
sigma/pipelines/kernellix/__init__.py
sigma/pipelines/kernellix/kernellix.py
sigma/pipelines/kernellix/linux.py
pysigma_backend_kernellix-0.1.3.dist-info/LICENSE
pysigma_backend_kernellix-0.1.3.dist-info/METADATA
pysigma_backend_kernellix-0.1.3.dist-info/WHEEL
pysigma_backend_kernellix-0.1.3.dist-info/RECORD
