Metadata-Version: 2.1
Name: pySigma-backend-kernellix
Version: 0.1.3
Summary: Sigma Converter for Kernellix Security Analytics Platform
Home-page: https://github.com/sawwn23/pySigma-backend-kernellix
License: MIT
Author: Saw Win Naung
Author-email: saw.wn@kernellix.com
Requires-Python: >=3.8,<4.0
Classifier: License :: OSI Approved :: MIT License
Classifier: Programming Language :: Python :: 3
Classifier: Programming Language :: Python :: 3.8
Classifier: Programming Language :: Python :: 3.9
Classifier: Programming Language :: Python :: 3.10
Classifier: Programming Language :: Python :: 3.11
Classifier: Programming Language :: Python :: 3.12
Requires-Dist: pysigma (>=0.11.14,<0.12.0)
Project-URL: Repository, https://github.com/sawwn23/pySigma-backend-kernellix
